{
  "sizes": {
    "sizing": {
      "none": {
        "value": "{sizes.base.none.value}",
        "attributes": { "category": "rxm" }
      },
      "px": {
        "value": "{sizes.base.px.value}",
        "attributes": { "category": "rxm" }
      },
      "xs": {
        "value": "{sizes.base.xs.value}",
        "attributes": { "category": "rxm" }
      },
      "sm": {
        "value": "{sizes.base.sm.value}",
        "attributes": { "category": "rxm" }
      },
      "md": {
        "value": "{sizes.base.md.value}",
        "attributes": { "category": "rxm" }
      },
      "lg": {
        "value": "{sizes.base.lg.value}",
        "attributes": { "category": "rxm" }
      },
      "xl": {
        "value": "{sizes.base.xl.value}",
        "attributes": { "category": "rxm" }
      },
      "2xl": {
        "value": "{sizes.base.2xl.value}",
        "attributes": { "category": "rxm" }
      },
      "3xl": {
        "value": "{sizes.base.3xl.value}",
        "attributes": { "category": "rxm" }
      },
      "4xl": {
        "value": "{sizes.base.4xl.value}",
        "attributes": { "category": "rxm" }
      },
      "5xl": {
        "value": "{sizes.base.5xl.value}",
        "attributes": { "category": "rxm" }
      },
      "6xl": {
        "value": "{sizes.base.6xl.value}",
        "attributes": { "category": "rxm" }
      },
      "7xl": {
        "value": "{sizes.base.7xl.value}",
        "attributes": { "category": "rxm" }
      },
      "8xl": {
        "value": "{sizes.base.8xl.value}",
        "attributes": { "category": "rxm" }
      },
      "9xl": {
        "value": "{sizes.base.9xl.value}",
        "attributes": { "category": "rxm" }
      },
      "10xl": {
        "value": "{sizes.base.10xl.value}",
        "attributes": { "category": "rxm" }
      },
      "11xl": {
        "value": "{sizes.base.11xl.value}",
        "attributes": { "category": "rxm" }
      },
      "12xl": {
        "value": "{sizes.base.12xl.value}",
        "attributes": { "category": "rxm" }
      },
      "13xl": {
        "value": "{sizes.base.13xl.value}",
        "attributes": { "category": "rxm" }
      },
      "14xl": {
        "value": "{sizes.base.14xl.value}",
        "attributes": { "category": "rxm" }
      },
      "15xl": {
        "value": "{sizes.base.15xl.value}",
        "attributes": { "category": "rxm" }
      },
      "16xl": {
        "value": "{sizes.base.16xl.value}",
        "attributes": { "category": "rxm" }
      }
    }
  }
}
